Metadata-Version: 1.0
Name: chimelems1
Version: 1.0
Summary: Chim_elems
Home-page: UNKNOWN
Author: UNKNOWN
Author-email: ya.9637@yandex.ru
License: UNKNOWN
Platform: UNKNOWN
